libmiyoushe/__init__.py
libmiyoushe/auth.py
libmiyoushe/base.py
libmiyoushe/bbs.py
libmiyoushe/configs.py
libmiyoushe/games.py
libmiyoushe/replace_regex.py
libmiyoushe/threadRender.py
libmiyoushe/urls.py
libmiyoushe-0.0.4.3.dist-info/METADATA
libmiyoushe-0.0.4.3.dist-info/WHEEL
libmiyoushe-0.0.4.3.dist-info/top_level.txt
libmiyoushe-0.0.4.3.dist-info/zip-safe
libmiyoushe-0.0.4.3.dist-info/RECORD
